pyapktool/__init__.py
pyapktool/pyapktool.py
pyapktool-0.2.1.dist-info/LICENSE
pyapktool-0.2.1.dist-info/METADATA
pyapktool-0.2.1.dist-info/WHEEL
pyapktool-0.2.1.dist-info/entry_points.txt
pyapktool-0.2.1.dist-info/top_level.txt
pyapktool-0.2.1.dist-info/RECORD
