Metadata-Version: 2.1
Name: pyapktool
Version: 0.2.1
Summary: Unpack/Pack Android's apk and sign it. No prerequisites required.
Author-email: agentzex <cypy919@gmail.com>
Project-URL: Source, https://github.com/agentzex/pyapktool/
Keywords: pyapktool,apktool,android apk,apk decompiler,apk decompile,android app decompiler,android app unpacker,android app packer,android apk unpacker,android apk packer,android app sign,android apk sign,android apk debug keys
Classifier: Intended Audience :: Developers
Classifier: License :: OSI Approved :: MIT License
Classifier: Operating System :: OS Independent
Classifier: Programming Language :: Python
Classifier: Programming Language :: Python :: 3
Classifier: Topic :: Utilities
Requires-Python: >=3.6
License-File: LICENSE
Requires-Dist: requests>=2.2.0
